brilliantimagery/__init__.py
brilliantimagery/dng/__init__.py
brilliantimagery/dng/_dng.py
brilliantimagery/dng/_dng_constants.py
brilliantimagery/dng/_dng_utils.py
brilliantimagery/dng/_renderer.cpp
brilliantimagery/dng/_renderer.pxd
brilliantimagery/dng/_renderer.pyx
brilliantimagery/ljpeg/__init__.py
brilliantimagery/ljpeg/_decode.cpp
brilliantimagery/ljpeg/_decode.pxd
brilliantimagery/ljpeg/_decode.pyx
brilliantimagery/ljpeg/_encode.cpp
brilliantimagery/ljpeg/_encode.pxd
brilliantimagery/ljpeg/_encode.pyx
brilliantimagery/meta_image/__init__.py
brilliantimagery/meta_image/_meta_constants.py
brilliantimagery/meta_image/_meta_image.py
brilliantimagery/ppm/__init__.py
brilliantimagery/ppm/_save.c
brilliantimagery/ppm/_save.pxd
brilliantimagery/ppm/_save.pyx
brilliantimagery/sequence/__init__.py
brilliantimagery/sequence/_ramp.py
brilliantimagery/sequence/_sequence.py
brilliantimagery/sequence/_stabilize.py
brilliantimagery/sequence/_stabilize_util.py
brilliantimagery/tools/__init__.py
brilliantimagery/tools/_jpg_reordering.py
tests/unit/dng/renderer_exporter.pyx
brilliantimagery/__init__.py
brilliantimagery/dng/_dng.py
brilliantimagery/dng/_dng_constants.py
brilliantimagery/dng/_dng_utils.py
brilliantimagery/dng/_renderer.cp38-win_amd64.pyd
brilliantimagery/dng/_renderer.cpp
brilliantimagery/dng/_renderer.pxd
brilliantimagery/dng/_renderer.pyx
brilliantimagery/dng/__init__.py
brilliantimagery/ljpeg/_decode.cp38-win_amd64.pyd
brilliantimagery/ljpeg/_decode.cpp
brilliantimagery/ljpeg/_decode.pxd
brilliantimagery/ljpeg/_decode.pyx
brilliantimagery/ljpeg/_encode.cp38-win_amd64.pyd
brilliantimagery/ljpeg/_encode.cpp
brilliantimagery/ljpeg/_encode.pxd
brilliantimagery/ljpeg/_encode.pyx
brilliantimagery/ljpeg/__init__.py
brilliantimagery/meta_image/_meta_constants.py
brilliantimagery/meta_image/_meta_image.py
brilliantimagery/meta_image/__init__.py
brilliantimagery/ppm/_save.c
brilliantimagery/ppm/_save.cp38-win_amd64.pyd
brilliantimagery/ppm/_save.pxd
brilliantimagery-0.2.2.dist-info/LICENSE
brilliantimagery-0.2.2.dist-info/WHEEL
brilliantimagery-0.2.2.dist-info/METADATA
brilliantimagery-0.2.2.dist-info/RECORD
