Metadata-Version: 2.1
Name: brilliantimagery
Version: 0.2.2
Summary: A python DNG editing package.
Home-page: https://www.brilliantimagery.org
License: GPL-3.0-only
Author: Chad DeRosier
Author-email: chad.derosier@gmail.com
Requires-Python: >=3.8.0,<4.0.0
Classifier: License :: OSI Approved :: GNU General Public License v3 (GPLv3)
Classifier: Programming Language :: Python :: 3
Classifier: Programming Language :: Python :: 3.8
Requires-Dist: cython (>=0.29.15,<0.30.0)
Requires-Dist: numpy (>=1.18.1,<2.0.0)
Requires-Dist: opencv-contrib-python (>=4.1.2,<5.0.0)
Requires-Dist: toml (>=0.10.0,<0.11.0)
Requires-Dist: tqdm (>=4.41.1,<5.0.0)
Project-URL: Repository, https://github.com/brilliantimagery/brilliantimagery
